{
  "auditedAt": "2026-02-25T17:07:32.353966+00:00",
  "total": 49,
  "passed": 49,
  "failed": 0,
  "results": [
    {
      "id": "stedi-product-designer",
      "company": "Stedi",
      "title": "Product Designer",
      "url": "https://jobs.ashbyhq.com/stedi/bacc5e48-0cd3-4abc-a9cc-a5b12863a804",
      "pass": true,
      "reason": "OK",
      "status": 200,
      "checkedAt": "2026-07-21T16:15:36.052Z"
    },
    {
      "id": "artisan-staff-product-designer",
      "company": "Artisan",
      "title": "Staff Product Designer",
      "url": "https://jobs.ashbyhq.com/artisan/93bca429-26b2-4cca-a8a1-26c024656ca4",
      "pass": true,
      "reason": "OK",
      "status": 200,
      "checkedAt": "2026-07-21T16:15:36.052Z"
    },
    {
      "id": "render-senior-product-designer",
      "company": "Render",
      "title": "Senior Product Designer",
      "url": "https://jobs.ashbyhq.com/render/0f0ccf3e-4caf-4586-9a66-411dbf49fcc5",
      "pass": true,
      "reason": "OK",
      "status": 200,
      "checkedAt": "2026-07-21T16:15:36.052Z"
    },
    {
      "id": "wefunder-visual-micro-interaction-designer",
      "company": "Wefunder",
      "title": "Visual & Micro-Interaction Designer",
      "url": "https://wefunder.com/jobs/micro-interaction-designer",
      "pass": false,
      "reason": "No live job signals found on page",
      "status": 200,
      "checkedAt": "2026-07-21T16:15:36.052Z"
    },
    {
      "id": "euphoric-lead-product-designer",
      "company": "Euphoric",
      "title": "Lead Product Designer",
      "url": "https://jobs.ashbyhq.com/euphoric/ce6bd6c1-229c-4568-83f8-0524b4bfb648",
      "pass": true,
      "reason": "OK",
      "status": 200,
      "checkedAt": "2026-07-21T16:15:36.052Z"
    }
  ],
  "lastRun": "2026-07-21T16:15:36.052Z",
  "summary": {
    "passed": 4,
    "failed": 1,
    "total": 5
  }
}